sucolo_database_services/__init__.py
sucolo_database_services/data_access.py
sucolo_database_services/elasticsearch_client/__init__.py
sucolo_database_services/elasticsearch_client/index_manager.py
sucolo_database_services/elasticsearch_client/read_repository.py
sucolo_database_services/elasticsearch_client/service.py
sucolo_database_services/elasticsearch_client/write_repository.py
sucolo_database_services/redis_client/__init__.py
sucolo_database_services/redis_client/consts.py
sucolo_database_services/redis_client/keys_manager.py
sucolo_database_services/redis_client/read_repository.py
sucolo_database_services/redis_client/service.py
sucolo_database_services/redis_client/utils.py
sucolo_database_services/redis_client/write_repository.py
sucolo_database_services/services/__init__.py
sucolo_database_services/services/base_service.py
sucolo_database_services/services/data_management_service.py
sucolo_database_services/services/district_features_service.py
sucolo_database_services/services/dynamic_features_service.py
sucolo_database_services/services/fields_and_queries.py
sucolo_database_services/services/health_check_service.py
sucolo_database_services/services/metadata_service.py
sucolo_database_services/services/multiple_features_service.py
sucolo_database_services/tests/__init__.py
sucolo_database_services/tests/conftest.py
sucolo_database_services/tests/test_data_access.py
sucolo_database_services/tests/test_district_features_service.py
sucolo_database_services/utils/__init__.py
sucolo_database_services/utils/config.py
sucolo_database_services/utils/exceptions.py
sucolo_database_services/utils/polygons2hexagons.py
sucolo_database_services-stubs/README.md
sucolo_database_services-stubs/pyproject.toml
sucolo_database_services-stubs/sucolo_database_services-stubs/__init__.pyi
sucolo_database_services-stubs/sucolo_database_services-stubs/data_access.pyi
sucolo_database_services-stubs/sucolo_database_services-stubs/elasticsearch_client/__init__.pyi
sucolo_database_services-0.4.3.dist-info/METADATA
sucolo_database_services-0.4.3.dist-info/WHEEL
sucolo_database_services-0.4.3.dist-info/top_level.txt
sucolo_database_services-0.4.3.dist-info/RECORD
