Metadata-Version: 2.4
Name: sucolo-database-services
Version: 0.4.3
Summary: A Python client for Sucolo's database services.
Author-email: Stanislaw Straburzynski <sstraburzynski@gmail.com>
License: MIT
Keywords: database,elasticsearch,redis,geospatial
Classifier: Development Status :: 4 - Beta
Classifier: Intended Audience :: Developers
Classifier: License :: OSI Approved :: MIT License
Classifier: Programming Language :: Python :: 3.10
Classifier: Programming Language :: Python :: 3.11
Classifier: Programming Language :: Python :: 3.12
Classifier: Programming Language :: Python :: 3.13
Classifier: Topic :: Database
Classifier: Topic :: Software Development :: Libraries :: Python Modules
Requires-Python: <3.14,>=3.10
